[{"line":2,"elements":[{"start_timestamp":"2021-11-09T17:48:02.486Z","line":13,"name":"find product apple","description":"","id":"home-page-features;find-product-apple;;2","type":"scenario","keyword":"Scenario Outline","steps":[{"result":{"duration":3439740100,"status":"passed"},"line":6,"name":"User navigates to the application","match":{"location":"com.bdd.steps.CoomonSteps.user_navigates_to_the_application()"},"keyword":"Given "},{"result":{"duration":140707300,"status":"passed"},"line":7,"name":"User type \"jab\" name","match":{"arguments":[{"val":"\"jab\"","offset":10}],"location":"com.bdd.steps.HomePageSteps.user_type_product_name(java.lang.String)"},"keyword":"When "},{"result":{"duration":147576900,"status":"passed"},"line":8,"name":"Choose product","match":{"location":"com.bdd.steps.HomePageSteps.click_on_search_button()"},"keyword":"And "},{"result":{"duration":722736300,"status":"passed"},"line":9,"name":"Product description appears on the page","match":{"location":"com.bdd.steps.HomePageSteps.product_description_appears_on_the_page()"},"keyword":"Then "}],"tags":[{"name":"@homePageFeatures"},{"name":"@searchProducts"}]}],"name":"Home Page features","description":"","id":"home-page-features","keyword":"Feature","uri":"file:src/test/resources/features/HomePage.feature","tags":[{"name":"@homePageFeatures","type":"Tag","location":{"line":1,"column":1}}]}]